epsf_generator/__init__.py
epsf_generator/main.py
epsf_generator-1.0.0.dist-info/METADATA
epsf_generator-1.0.0.dist-info/WHEEL
epsf_generator-1.0.0.dist-info/entry_points.txt
epsf_generator-1.0.0.dist-info/top_level.txt
epsf_generator-1.0.0.dist-info/RECORD
