Metadata-Version: 2.1
Name: epsf-generator
Version: 1.0.0
Summary: A tiny script generating ePSF for deep sky image
Author: Zhen Huang
Author-email: hzvictor@zju.edu.cn
License: BSD 3-Clause License
Keywords: epsf,astrophotography,psf
Requires-Dist: numpy
Requires-Dist: astropy (==5.2.2)
Requires-Dist: photutils (==1.5)
Requires-Dist: matplotlib (==3.7.1)
